stereo_gp/__init__.py
stereo_gp/stereo_gp.py
stereobot_gp-0.0.2.dist-info/METADATA
stereobot_gp-0.0.2.dist-info/WHEEL
stereobot_gp-0.0.2.dist-info/top_level.txt
stereobot_gp-0.0.2.dist-info/RECORD
