Metadata-Version: 2.1
Name: stereobot_gp
Version: 0.0.2
Author-email: Gabriela Pinheiro <gpinheiro2812@gmail.com>
Project-URL: Homepage, https://github.com/onkarbhardwaj/Stereobot-GP
Project-URL: Issues, https://github.com/onkarbhardwaj/Stereobot-GP
Classifier: Programming Language :: Python :: 3
Classifier: License :: OSI Approved :: MIT License
Classifier: Operating System :: OS Independent
Requires-Python: >=3.8
